splat_trainer/__init__.py
splat_trainer/image_scaler.py
splat_trainer/scheduler.py
splat_trainer/trainer.py
splat_trainer/camera_table/camera_table.py
splat_trainer/camera_table/pose_table.py
splat_trainer/config/__init__.py
splat_trainer/config/config.yaml
splat_trainer/config/controller/static.yaml
splat_trainer/config/controller/target.yaml
splat_trainer/config/controller/threshold.yaml
splat_trainer/config/dataset/colmap.yaml
splat_trainer/config/dataset/scan.yaml
splat_trainer/config/logger/tensorboard.yaml
splat_trainer/config/logger/wandb.yaml
splat_trainer/config/scene/sh.yaml
splat_trainer/config/scene/tcnn.yaml
splat_trainer/controller/__init__.py
splat_trainer/controller/controller.py
splat_trainer/controller/target_controller.py
splat_trainer/controller/threshold_controller.py
splat_trainer/dataset/__init__.py
splat_trainer/dataset/dataset.py
splat_trainer/dataset/colmap/__init__.py
splat_trainer/dataset/colmap/dataset.py
splat_trainer/dataset/colmap/loading.py
splat_trainer/dataset/scan/__init__.py
splat_trainer/dataset/scan/dataset.py
splat_trainer/dataset/scan/loading.py
splat_trainer/dataset/scan/visibility.py
splat_trainer/gaussians/loading.py
splat_trainer/gaussians/split.py
splat_trainer/logger/__init__.py
splat_trainer/logger/histogram.py
splat_trainer/logger/logger.py
splat_trainer/logger/tensorboard.py
splat_trainer/logger/wandb.py
splat_trainer/modules/__init__.py
splat_trainer/scene/__init__.py
splat_trainer/scene/io.py
splat_trainer/scene/scene.py
splat_trainer/scene/sh_scene.py
splat_trainer/scene/tcnn_scene.py
splat_trainer/scripts/test_split.py
splat_trainer/scripts/test_tcnn.py
splat_trainer/scripts/train_scan.py
splat_trainer/util/__init__.py
splat_trainer/util/colorize.py
splat_trainer/util/config.py
splat_trainer/util/containers.py
splat_trainer/util/misc.py
splat_trainer/util/pointcloud.py
splat_trainer/util/transforms.py
splat_trainer-0.1.2.dist-info/METADATA
splat_trainer-0.1.2.dist-info/WHEEL
splat_trainer-0.1.2.dist-info/entry_points.txt
splat_trainer-0.1.2.dist-info/top_level.txt
splat_trainer-0.1.2.dist-info/RECORD
